blipnlptest/.idea/blipnlptest.iml
blipnlptest/.idea/inspectionProfiles/profiles_settings.xml
blipnlptest/.idea/inspectionProfiles/Project_Default.xml
blipnlptest/.idea/modules.xml
blipnlptest/.idea/workspace.xml
blipnlptest/__init__.py
blipnlptest/blipnlptest.py
blipnlptest-0.2.5.dist-info/LICENSE.txt
blipnlptest-0.2.5.dist-info/METADATA
blipnlptest-0.2.5.dist-info/WHEEL
blipnlptest-0.2.5.dist-info/RECORD
